client/__init__.py
client/setup.py
client/sponsored_ads_client/__init__.py
client/sponsored_ads_client/s4f_client.py
client/sponsored_ads_client/protobuf/__init__.py
client/sponsored_ads_client/protobuf/__main__.py
client/sponsored_ads_client/protobuf/sponsored_ads_service_pb2.py
client/sponsored_ads_client/protobuf/sponsored_ads_service_pb2.pyi
client/tests/__init__.py
client/tests/test_s4f_client.py
sponsored_ads_service/__init__.py
sponsored_ads_service/ab_test_positions.py
sponsored_ads_service/cli.py
sponsored_ads_service/constants.py
sponsored_ads_service/errors.py
sponsored_ads_service/service.py
sponsored_ads_service/configuration/__init__.py
sponsored_ads_service/configuration/clients.py
sponsored_ads_service/configuration/sponsored_ads_config.py
sponsored_ads_service/factories/__init__.py
sponsored_ads_service/factories/hierarchy.py
sponsored_ads_service/factories/tools/__init__.py
sponsored_ads_service/factories/tools/filter.py
sponsored_ads_service/integrations/__init__.py
sponsored_ads_service/integrations/catalogue_aggregator.py
sponsored_ads_service/integrations/hierarchy.py
sponsored_ads_service/integrations/route.py
sponsored_ads_service/models/__init__.py
sponsored_ads_service/models/caching.py
sponsored_ads_service/models/decorated.py
sponsored_ads_service/models/hierarchy.py
sponsored_ads_service/models/link_data.py
sponsored_ads_service/models/notices.py
sponsored_ads_service/models/onlinesales.py
sponsored_ads_service/models/positioning.py
sponsored_ads_service/models/request_response.py
sponsored_ads_service/models/sponsored_display.py
sponsored_ads_service/models/sponsored_product.py
sponsored_ads_service/models/validation.py
sponsored_ads_service/onlinesales/__init__.py
sponsored_ads_service/onlinesales/creatives.py
sponsored_ads_service/onlinesales/destination_url_factory.py
sponsored_ads_service/onlinesales/facade.py
sponsored_ads_service/onlinesales/integration.py
sponsored_ads_service/onlinesales/models.py
sponsored_ads_service-3.0.3rc1.dist-info/METADATA
sponsored_ads_service-3.0.3rc1.dist-info/WHEEL
sponsored_ads_service-3.0.3rc1.dist-info/entry_points.txt
sponsored_ads_service-3.0.3rc1.dist-info/top_level.txt
sponsored_ads_service-3.0.3rc1.dist-info/RECORD
