Metadata-Version: 2.2
Name: sponsored-ads-service
Version: 3.0.3rc1
Summary: S4F service responsible for sponsored ads
Home-page: https://github.com/TAKEALOT/sponsored-ads-service
Author: DSCBE
Author-email: en-dsc-be@takealot.com
Classifier: Programming Language :: Python :: 3.12
Classifier: Natural Language :: English
Classifier: Intended Audience :: Developers
Dynamic: author
Dynamic: author-email
Dynamic: classifier
Dynamic: description
Dynamic: description-content-type
Dynamic: home-page
Dynamic: summary
